tests/__init__.py
tests/test_tensor.py
torchmini/__init__.py
torchmini/tensor.py
torchmini/autograd/__init__.py
torchmini/autograd/function.py
torchmini/nn/__init__.py
torchmini/nn/activation.py
torchmini/nn/functional.py
torchmini/nn/loss.py
torchmini/nn/module.py
torchmini/nn/parameter.py
torchmini/nn/modules/__init__.py
torchmini/nn/modules/dropout.py
torchmini/nn/modules/linear.py
torchmini/nn/modules/relu.py
torchmini/optim/__init__.py
torchmini/optim/optimizer.py
torchmini/optim/optimizers/__init__.py
torchmini/optim/optimizers/adam.py
torchmini/optim/optimizers/sgd.py
torchmini/utils/__init__.py
torchmini/utils/data/__init__.py
torchmini/utils/data/batch.py
torchmini/utils/data/dataloader.py
torchmini-0.0.1.dist-info/LICENSE
torchmini-0.0.1.dist-info/METADATA
torchmini-0.0.1.dist-info/WHEEL
torchmini-0.0.1.dist-info/top_level.txt
torchmini-0.0.1.dist-info/RECORD
